{
    "n" :  1,       
    "Nx" : 200,     
    "Ny" : 200,    
    "dt" : 0.5,    
    "n_out"  : 1,   
    "Nx_out" : 200,
    "Ny_out" : 200, 
    "itstp"  : 10,  
    "maxout" : 1000,
    "eps_pol"   : 1e-5,  
    "jumpfactor": 1,   
    "eps_gamma" : 1e-5,   
    "eps_time"  : 1e-12, 
    "mu_e"      : -0.000272121,
    "curvature" : 0.00015, 
    "tau"       : 0,       
    "nu_perp"   : 5e-3,     
    "D"         : 0.005e-8,
    "C"         : 2.5e-6,        
    "l_para"    : 1000000 ,
    "amplitude" : 1.0,
    "sigma"  : 10,
    "posX"  : 0.3,
    "posY"  : 0.5,
    "prof_amp": 0.0,
    "bg_prof_amp" : 1.0,
    "lx"  : 200,
    "ly"  : 200,
    "bc_x"    : "NEU_DIR",
    "bc_y"    : "PER",
    "bc_x_phi": "DIR_NEU",
    "hwmode": 1,
    "invkappa": 100,
    "SOL_b" : 0.3,
    "prof_source_rate" : 0.005 ,
    "source_b" : 0.1,
    "source_damping_width" : 5,
    "prof_sink_rate" :0.001,
    "sink_b" : 0.9,
    "damping_width" : 0.5,
    "fluxmode" : 1
}

